dp_dl/cli.py
igdp_downloader-1.0.1.dist-info/LICENCE
igdp_downloader-1.0.1.dist-info/METADATA
igdp_downloader-1.0.1.dist-info/WHEEL
igdp_downloader-1.0.1.dist-info/entry_points.txt
igdp_downloader-1.0.1.dist-info/top_level.txt
igdp_downloader-1.0.1.dist-info/RECORD
